power01_div/__init__.py
power01_div/div.py
power01_div-0.1.2.dist-info/METADATA
power01_div-0.1.2.dist-info/WHEEL
power01_div-0.1.2.dist-info/entry_points.txt
power01_div-0.1.2.dist-info/top_level.txt
power01_div-0.1.2.dist-info/RECORD
