Metadata-Version: 2.1
Name: power01_div
Version: 0.1.2
Summary: Default template for PDM package
Author-email: sooj1n <sujin19371@gmail.com>
License: MIT
Requires-Python: >=3.9
